zdataclass/__init__.py
zdataclass/zdataclass.py
zdataclass/zgmicro_assigned_numbers.py
zdataclass-0.4.dist-info/LICENSE
zdataclass-0.4.dist-info/METADATA
zdataclass-0.4.dist-info/WHEEL
zdataclass-0.4.dist-info/top_level.txt
zdataclass-0.4.dist-info/RECORD
