Metadata-Version: 2.1
Name: zdataclass
Version: 0.4
Summary: Extension for dataclass
Home-page: https://github.com/zljun/zdataclass
Author: zuolongjun
Author-email: zuo.longjun@zgmicro.com
Classifier: Programming Language :: Python :: 3
Classifier: License :: OSI Approved :: GNU General Public License v3 or later (GPLv3+)
Classifier: Operating System :: OS Independent
License-File: LICENSE
